jsonthrift/__init__.py
jsonthrift/jsonthrift.py
jsonthrift/TBinaryProtocol.py
jsonthrift/TBufferedTransport.py
jsonthrift/TFramedTransport.py
jsonthrift/thriftstruct.py
jsonthrift/TTransport.py
jsonthrift/TTypes.py
jsonthrift-0.1.4.dist-info/DESCRIPTION.rst
jsonthrift-0.1.4.dist-info/METADATA
jsonthrift-0.1.4.dist-info/metadata.json
jsonthrift-0.1.4.dist-info/pbr.json
jsonthrift-0.1.4.dist-info/RECORD
jsonthrift-0.1.4.dist-info/top_level.txt
jsonthrift-0.1.4.dist-info/WHEEL
