Metadata-Version: 2.0
Name: jsonthrift
Version: 0.1.4
Summary: a package for serializing json to/from thrift
Home-page: https://github.com/WKPlus/jsonthrift
Author: WKPlus
Author-email: qifa.zhao@gmail.com
License: MIT
Platform: UNKNOWN
Requires-Dist: thrift
Requires-Dist: thriftpy
